LICENSE
README.md
setup.cfg
setup.py
cloudgenix_config/__init__.py
cloudgenix_config/default_interfaces.py
cloudgenix_config/do.py
cloudgenix_config/pull.py
cloudgenix_config.egg-info/PKG-INFO
cloudgenix_config.egg-info/SOURCES.txt
cloudgenix_config.egg-info/dependency_links.txt
cloudgenix_config.egg-info/entry_points.txt
cloudgenix_config.egg-info/requires.txt
cloudgenix_config.egg-info/top_level.txt