Metadata-Version: 2.1
Name: cloudgenix-config
Version: 2.0.0b1
Summary: Configuration exporting and Continuous Integration (CI) capable configuration importing for the CloudGenix Cloud Controller.
Home-page: https://github.com/CloudGenix/cloudgenix_config
Author: CloudGenix Developer Support
Author-email: developers@cloudgenix.com
License: MIT
Classifier: Development Status :: 4 - Beta
Classifier: Intended Audience :: Developers
Classifier: License :: OSI Approved :: MIT License
Classifier: Programming Language :: Python :: 2.7
Classifier: Programming Language :: Python :: 3.6
Classifier: Programming Language :: Python :: 3.7
Classifier: Programming Language :: Python :: 3.8
License-File: LICENSE
